odoo/addons/website_sale_product_sort/README.rst
odoo/addons/website_sale_product_sort/__init__.py
odoo/addons/website_sale_product_sort/__manifest__.py
odoo/addons/website_sale_product_sort/controllers/__init__.py
odoo/addons/website_sale_product_sort/controllers/main.py
odoo/addons/website_sale_product_sort/i18n/ca.po
odoo/addons/website_sale_product_sort/i18n/es.po
odoo/addons/website_sale_product_sort/i18n/fr.po
odoo/addons/website_sale_product_sort/i18n/it.po
odoo/addons/website_sale_product_sort/i18n/nl.po
odoo/addons/website_sale_product_sort/i18n/website_sale_product_sort.pot
odoo/addons/website_sale_product_sort/models/__init__.py
odoo/addons/website_sale_product_sort/models/res_config_settings.py
odoo/addons/website_sale_product_sort/models/website.py
odoo/addons/website_sale_product_sort/readme/CONFIGURE.md
odoo/addons/website_sale_product_sort/readme/CONTRIBUTORS.md
odoo/addons/website_sale_product_sort/readme/DESCRIPTION.md
odoo/addons/website_sale_product_sort/readme/ROADMAP.md
odoo/addons/website_sale_product_sort/readme/USAGE.md
odoo/addons/website_sale_product_sort/static/description/icon.png
odoo/addons/website_sale_product_sort/static/description/index.html
odoo/addons/website_sale_product_sort/views/res_config_settings_view.xml
odoo/addons/website_sale_product_sort/views/website_sale_templates.xml
odoo_addon_website_sale_product_sort-18.0.1.0.0.4.dist-info/METADATA
odoo_addon_website_sale_product_sort-18.0.1.0.0.4.dist-info/WHEEL
odoo_addon_website_sale_product_sort-18.0.1.0.0.4.dist-info/top_level.txt
odoo_addon_website_sale_product_sort-18.0.1.0.0.4.dist-info/RECORD
